agentarchives/__init__.py
agentarchives/archivesspace/__init__.py
agentarchives/archivesspace/client.py
agentarchives/archivists_toolkit/__init__.py
agentarchives/archivists_toolkit/client.py
agentarchives/atom/__init__.py
agentarchives/atom/client.py
agentarchives-0.10.0.dist-info/LICENSE
agentarchives-0.10.0.dist-info/METADATA
agentarchives-0.10.0.dist-info/WHEEL
agentarchives-0.10.0.dist-info/top_level.txt
agentarchives-0.10.0.dist-info/RECORD
